Metadata-Version: 2.1
Name: tensorflow-history-plot
Version: 0.1.2
Summary: A tool for visualize Tensorflow history result.
Home-page: https://github.com/nofacer/TensorflowHistoryPlot
Author: 九日木彡
Author-email: nofacer@outlook.com
License: MIT
Platform: UNKNOWN
Classifier: License :: OSI Approved :: MIT License
Classifier: Programming Language :: Python
Classifier: Programming Language :: Python :: 3
Classifier: Programming Language :: Python :: 3.6
Classifier: Programming Language :: Python :: 3.7
Classifier: Programming Language :: Python :: 3.8
Classifier: Programming Language :: Python :: 3.9
Classifier: Programming Language :: Python :: Implementation :: CPython
Classifier: Programming Language :: Python :: Implementation :: PyPy
Requires-Python: >=3.6.0
